{
  "worlds": [
    {
      "id": 1,
      "name_en": "Forest Frontier",
      "name_fr": "Frontière forestière",
      "levels": [
        {
          "id": 1,
          "dialogues_file": "Levels/lvl_1_dialogues.json",
          "animations": [ "res/turret/animations/splash.plist", "res/turret/animations/cut.plist" ],
          "background": "res/levels/background2.png",
          "effects": [ "music/splash.mp3", "music/slash.mp3" ],
          "exp": 20,
          "holy_sugar": 1,
          "finalized": false,
          "path_level": "Level_1.json",
          "musics": [ "music/On-Tiptoe.mp3.mp3" ],
          "reward": {
            "file": "res/levels/rewards/saucer.png",
            "type": "tower",
            "tower_name": "saucer"
          },
          "sugar": 90,
          "type":  "normal",
          "tileset": [
            "res/levels/objects/ground.plist",
            "res/levels/objects/trees.plist",
            "res/levels/objects/forest.plist"
          ],
          "tilesetpng": [
            "res/levels/objects/ground.png",
            "res/levels/objects/trees.png",
            "res/levels/objects/forest.png"
          ],
          "x": -0.45,
          "y": 0.085,
          "challenges": [
            {
              "name": "Untouchable",
              "int_value": 3,
              "str_value": ""
            },
            {
              "name": "Misanthrope",
              "int_value": -1,
              "str_value": ""

            },
            {
              "name": "Stingy",
              "int_value": 90,
              "str_value": ""
            }
          ]
        },
        {
          "id": 2,
          "dialogues_file": "Levels/lvl_2_dialogues.json",
          "animations": [ "res/turret/animations/splash.plist", "res/turret/animations/cut.plist" ],
          "background": "res/levels/background2.png",
          "effects": [ "music/splash.mp3", "music/slash.mp3" ],
          "exp": 25,
          "holy_sugar": 2,
          "finalized": false,
          "path_level": "Level_2.json",
          "musics": [ "music/On-Tiptoe.mp3.mp3" ],
          "reward": {
            "type": "none"
          },
          "sugar": 90,
          "type":  "normal",
          "tileset": [
            "res/levels/objects/ground.plist",
            "res/levels/objects/trees.plist",
            "res/levels/objects/forest.plist"
          ],
          "tilesetpng": [
            "res/levels/objects/ground.png",
            "res/levels/objects/trees.png",
            "res/levels/objects/forest.png"
          ],
          "x": -0.35,
          "y": 0.11,
          "challenges": [
            {
              "name": "Untouchable",
              "int_value": 3,
              "str_value": ""
            },
            {
              "name": "Philanthrope",
              "int_value": -1,
              "str_value": ""

            },
            {
              "name": "Reckless",
              "int_value": -1,
              "str_value": ""
            }
          ]
        },
        {
          "id": 3,
          "dialogues_file": "Levels/lvl_3_dialogues.json",
          "animations": [ "res/turret/animations/splash.plist", "res/turret/animations/cut.plist" ],
          "background": "res/levels/background2.png",
          "effects": [ "music/splash.mp3", "music/slash.mp3" ],
          "exp": 25,
          "holy_sugar": 2,
          "finalized": false,
          "path_level": "Level_3.json",
          "musics": [ "music/On-Tiptoe.mp3.mp3" ],
          "reward": {
            "type": "none"
          },
          "sugar": 90,
          "type":  "normal",
          "tileset": [
            "res/levels/objects/ground.plist",
            "res/levels/objects/trees.plist",
            "res/levels/objects/forest.plist"
          ],
          "tilesetpng": [
            "res/levels/objects/ground.png",
            "res/levels/objects/trees.png",
            "res/levels/objects/forest.png"
          ],
          "x": -0.23,
          "y": 0.115,
          "challenges": [
            {
              "name": "Untouchable",
              "int_value": 3,
              "str_value": ""
            },
            {
              "name": "Philanthrope",
              "int_value": -1,
              "str_value": ""

            },
            {
              "name": "Narrow",
              "int_value": -1,
              "str_value": "bomber"
            }
          ]
        },
        {
          "id": 4,
          "dialogues_file": "Levels/lvl_4_dialogues.json",
          "animations": [ "res/turret/animations/splash.plist", "res/turret/animations/cut.plist" ],
          "background": "res/levels/background2.png",
          "effects": [ "music/splash.mp3", "music/slash.mp3" ],
          "exp": 25,
          "holy_sugar": 2,
          "finalized": false,
          "path_level": "Level_4.json",
          "musics": [ "music/On-Tiptoe.mp3.mp3" ],
          "reward": {
            "type": "none"
          },
          "sugar": 90,
          "type":  "normal",
          "tileset": [
            "res/levels/objects/ground.plist",
            "res/levels/objects/trees.plist",
            "res/levels/objects/forest.plist"
          ],
          "tilesetpng": [
            "res/levels/objects/ground.png",
            "res/levels/objects/trees.png",
            "res/levels/objects/forest.png"
          ],
          "x": -0.13,
          "y": 0.060,
          "challenges": [
            {
              "name": "Untouchable",
              "int_value": 3,
              "str_value": ""
            },
            {
              "name": "Misanthrope",
              "int_value": -1,
              "str_value": ""

            },
            {
              "name": "Reckless",
              "int_value": -1,
              "str_value": ""
            }
          ]
        },
        {
          "id": 5,
          "dialogues_file": "Levels/lvl_5_dialogues.json",
          "animations": [ "res/turret/animations/splash.plist", "res/turret/animations/cut.plist" ],
          "background": "res/levels/background2.png",
          "effects": [ "music/splash.mp3", "music/slash.mp3" ],
          "exp": 25,
          "holy_sugar": 2,
          "finalized": false,
          "path_level": "Level_5.json",
          "musics": [ "music/On-Tiptoe.mp3.mp3" ],
          "reward": {
            "file": "res/levels/rewards/cutter.png",
            "type": "tower",
            "tower_name": "cutter"
          },
          "sugar": 90,
          "type": "boss",
          "tileset": [
            "res/levels/objects/ground.plist",
            "res/levels/objects/trees.plist",
            "res/levels/objects/forest.plist"
          ],
          "tilesetpng": [
            "res/levels/objects/ground.png",
            "res/levels/objects/trees.png",
            "res/levels/objects/forest.png"
          ],
          "x": -0.017,
          "y": -0.01,
          "challenges": [
            {
              "name": "Untouchable",
              "int_value": 3,
              "str_value": ""
            },
            {
              "name": "Misanthrope",
              "int_value": -1,
              "str_value": ""

            },
            {
              "name": "Stingy",
              "int_value": 250,
              "str_value": ""
            }
          ]
        },
        {
          "id": 6,
          "dialogues_file": "Levels/lvl_6_dialogues.json",
          "animations": [ "res/turret/animations/splash.plist", "res/turret/animations/cut.plist" ],
          "background": "res/levels/background2.png",
          "effects": [ "music/splash.mp3", "music/slash.mp3" ],
          "exp": 25,
          "holy_sugar": 2,
          "finalized": false,
          "path_level": "Level_6.json",
          "musics": [ "music/On-Tiptoe.mp3.mp3" ],
          "reward": {
            "type": "none"
          },
          "sugar": 90,
          "type": "normal",
          "tileset": [
            "res/levels/objects/ground.plist",
            "res/levels/objects/trees.plist",
            "res/levels/objects/forest.plist"
          ],
          "tilesetpng": [
            "res/levels/objects/ground.png",
            "res/levels/objects/trees.png",
            "res/levels/objects/forest.png"
          ],
          "x": 0.16,
          "y": -0.12
        },
        {
          "id": 7,
          "dialogues_file": "Levels/lvl_7_dialogues.json",
          "animations": [ "res/turret/animations/splash.plist", "res/turret/animations/cut.plist" ],
          "background": "res/levels/background2.png",
          "effects": [ "music/splash.mp3", "music/slash.mp3" ],
          "exp": 25,
          "holy_sugar": 2,
          "finalized": false,
          "path_level": "Level_6.json",
          "musics": [ "music/On-Tiptoe.mp3.mp3" ],
          "reward": {
            "type": "none"
          },
          "sugar": 400,
          "type": "normal",
          "tileset": [
            "res/levels/objects/ground.plist",
            "res/levels/objects/trees.plist",
            "res/levels/objects/forest.plist"
          ],
          "tilesetpng": [
            "res/levels/objects/ground.png",
            "res/levels/objects/trees.png",
            "res/levels/objects/forest.png"
          ],
          "x": 0.1,
          "y": 0.03
        }
      ]
    },
    {
      "id": 1
    }
  ]
}